LICENSE
MANIFEST.in
README.md
requirements-dev.txt
requirements.txt
setup.cfg
setup.py
kindle2notion/__init__.py
kindle2notion/__main__.py
kindle2notion/exporting.py
kindle2notion/parsing.py
kindle2notion/reading.py
kindle2notion.egg-info/PKG-INFO
kindle2notion.egg-info/SOURCES.txt
kindle2notion.egg-info/dependency_links.txt
kindle2notion.egg-info/entry_points.txt
kindle2notion.egg-info/requires.txt
kindle2notion.egg-info/top_level.txt