Metadata-Version: 2.1
Name: kindle2notion
Version: 0.1.8
Summary: Export all the clippings from your Kindle device to a database in Notion.
Home-page: https://github.com/paperboi/kindle2notion
Author: Jeffrey Jacob
Author-email: jeffreysamjacob@gmail.com
License: UNKNOWN
Platform: UNKNOWN
Classifier: Programming Language :: Python :: 3
Classifier: License :: OSI Approved :: MIT License
Classifier: Operating System :: OS Independent
Requires-Python: >=3.9
Provides-Extra: dev
